compactem/__init__.py
compactem/main.py
compactem/core/__init__.py
compactem/core/dp.py
compactem/core/oracle_transfer.py
compactem/model_builder/DecisionTreeModelBuilder.py
compactem/model_builder/GradientBoostingClassifier.py
compactem/model_builder/LarsAndRidge.py
compactem/model_builder/LinearProbabilityModel.py
compactem/model_builder/RandomForestClassifier.py
compactem/model_builder/__init__.py
compactem/model_builder/base_model.py
compactem/oracles/__init__.py
compactem/oracles/oracle_learners.py
compactem/utils/__init__.py
compactem/utils/cv_utils.py
compactem/utils/data_format.py
compactem/utils/data_load.py
compactem/utils/output_processors.py
compactem/utils/utils.py
compactem-0.9.8.dist-info/METADATA
compactem-0.9.8.dist-info/WHEEL
compactem-0.9.8.dist-info/top_level.txt
compactem-0.9.8.dist-info/RECORD
