Metadata-Version: 2.1
Name: compactem
Version: 0.9.8
Summary: compactem
Home-page: https://bitbucket.org/aghose/compactem
Author: Abhishek Ghose
License: Apache 2.0
Platform: UNKNOWN
Classifier: Topic :: Scientific/Engineering
Classifier: Topic :: Scientific/Engineering :: Artificial Intelligence
Classifier: License :: OSI Approved :: Apache Software License
Classifier: Programming Language :: Python :: 3 :: Only
Requires-Python: >=3.6
Requires-Dist: seaborn (>=0.11.0)
Requires-Dist: numpy (>=1.18.2)
Requires-Dist: scipy (>=1.4.1)
Requires-Dist: lightgbm (>=3.0.0)
Requires-Dist: hyperopt (>=0.2.5)
Requires-Dist: matplotlib (>=3.3.3)
Requires-Dist: pandas (>=1.1.4)
Requires-Dist: scikit-learn (>=0.23.2)
Requires-Dist: lipo (>=1.2.2)
Requires-Dist: pysot (>=0.3.3)
